[{"name": "ABF載板", "return_pct": 20.5}, {"name": "光通訊", "return_pct": 19.0}, {"name": "塑膠工業", "return_pct": 14.18}, {"name": "機器人", "return_pct": 12.87}, {"name": "PCB印刷電路板", "return_pct": 7.43}, {"name": "造紙工業", "return_pct": 6.53}, {"name": "電動車", "return_pct": 5.73}, {"name": "電腦及週邊設備業", "return_pct": 5.06}, {"name": "化學工業", "return_pct": 3.64}, {"name": "橡膠工業", "return_pct": 2.88}, {"name": "光電業", "return_pct": 2.56}, {"name": "記憶體", "return_pct": 2.46}, {"name": "創新板股票", "return_pct": 2.31}, {"name": "食品工業", "return_pct": 1.15}, {"name": "電子零組件業", "return_pct": 0.88}]